gabbi_tempest/__init__.py
gabbi_tempest/config.py
gabbi_tempest/plugin.py
gabbi_tempest/tests/__init__.py
gabbi_tempest/tests/scenario/__init__.py
gabbi_tempest-0.2.2.dist-info/AUTHORS
gabbi_tempest-0.2.2.dist-info/METADATA
gabbi_tempest-0.2.2.dist-info/WHEEL
gabbi_tempest-0.2.2.dist-info/entry_points.txt
gabbi_tempest-0.2.2.dist-info/pbr.json
gabbi_tempest-0.2.2.dist-info/top_level.txt
gabbi_tempest-0.2.2.dist-info/RECORD
