Metadata-Version: 2.1
Name: gabbi-tempest
Version: 0.2.2
Summary: Run Gabbi Tests as Tempest Plugin
Home-page: https://git.openstack.org/openstack/gabbi-tempest
Author: Chris Dent
Author-email: cdent@anticdent.org
License: Apache-2
Platform: UNKNOWN
Classifier: Intended Audience :: Developers
Classifier: Intended Audience :: Information Technology
Classifier: License :: OSI Approved :: Apache Software License
Classifier: Operating System :: POSIX
Classifier: Programming Language :: Python
Classifier: Programming Language :: Python :: 2
Classifier: Programming Language :: Python :: 2.7
Classifier: Programming Language :: Python :: 3
Classifier: Programming Language :: Python :: 3.5
Classifier: Programming Language :: Python :: 3.6
Classifier: Topic :: Software Development :: Testing
Requires-Dist: pbr
Requires-Dist: gabbi
Requires-Dist: six
